LICENSE
MANIFEST.in
README.rst
setup.py
tests.py
github_summary.egg-info/PKG-INFO
github_summary.egg-info/SOURCES.txt
github_summary.egg-info/dependency_links.txt
github_summary.egg-info/entry_points.txt
github_summary.egg-info/not-zip-safe
github_summary.egg-info/requires.txt
github_summary.egg-info/top_level.txt
githubsummary/__init__.py
githubsummary/config.py
githubsummary/config_flymake.py
githubsummary/githubsummary.py
githubsummary/templates/rst/index-en.rst
githubsummary/templates/rst/index-fr.rst
githubsummary/templates/rst/projects-en.rst
githubsummary/templates/rst/projects-fr.rst
githubsummary/templates/txt/index.txt
githubsummary/tools/org2json